light_util/__init__.py
light_util/time_util.py
light_util-0.0.1.dist-info/METADATA
light_util-0.0.1.dist-info/WHEEL
light_util-0.0.1.dist-info/licenses/LICENSE
light_util-0.0.1.dist-info/RECORD
