Metadata-Version: 2.4
Name: light-util
Version: 0.0.1
Summary: A utility package for Python projects, providing decorators and other utilities.
Project-URL: Homepage, https://github.com/zzhdbw/light-util
Author-email: Zhihao Zhang <2578503482@qq.com>
License: MIT License
License-File: LICENSE
Classifier: License :: OSI Approved :: MIT License
Classifier: Operating System :: OS Independent
Classifier: Programming Language :: Python :: 3
Requires-Python: >=3.3
